pyjobshop/Model.py
pyjobshop/ProblemData.py
pyjobshop/Result.py
pyjobshop/Solution.py
pyjobshop/__init__.py
pyjobshop/cli.py
pyjobshop/constants.py
pyjobshop/plot/__init__.py
pyjobshop/plot/plot_machine_gantt.py
pyjobshop/plot/plot_resource_usage.py
pyjobshop/plot/plot_task_gantt.py
pyjobshop/plot/utils.py
pyjobshop/read.py
pyjobshop/show_versions.py
pyjobshop/solve.py
pyjobshop/solvers/__init__.py
pyjobshop/solvers/cpoptimizer/CPModel.py
pyjobshop/solvers/cpoptimizer/Constraints.py
pyjobshop/solvers/cpoptimizer/Objective.py
pyjobshop/solvers/cpoptimizer/Variables.py
pyjobshop/solvers/cpoptimizer/__init__.py
pyjobshop/solvers/cpoptimizer/utils.py
pyjobshop/solvers/ortools/CPModel.py
pyjobshop/solvers/ortools/Constraints.py
pyjobshop/solvers/ortools/Objective.py
pyjobshop/solvers/ortools/Variables.py
pyjobshop/solvers/ortools/__init__.py
pyjobshop/solvers/ortools/utils.py
pyjobshop/solvers/utils.py
pyjobshop-0.0.8.dist-info/licenses/LICENSE.md
pyjobshop-0.0.8.dist-info/WHEEL
pyjobshop-0.0.8.dist-info/entry_points.txt
pyjobshop-0.0.8.dist-info/METADATA
pyjobshop-0.0.8.dist-info/RECORD
