Metadata-Version: 2.4
Name: pyjobshop
Version: 0.0.8
Summary: Solving scheduling problems with constraint programming.
Keywords: scheduling,job shop,project scheduling,constraint programming,operations research
Author: Leon Lan, Joost Berkhout
Author-email: Leon Lan <leon.lanyidong@gmail.com>, Joost Berkhout <joost.berkhout@vu.nl>
License-Expression: MIT
License-File: LICENSE.md
Classifier: Intended Audience :: Developers
Classifier: Intended Audience :: Science/Research
Classifier: Development Status :: 5 - Production/Stable
Classifier: Topic :: Software Development
Classifier: Topic :: Scientific/Engineering
Classifier: License :: OSI Approved :: MIT License
Classifier: Programming Language :: Python :: 3
Requires-Dist: ortools>=9.12.4544
Requires-Dist: matplotlib>=3.9.2
Requires-Dist: fjsplib>=0.0.2
Requires-Dist: psplib>=0.4.0
Requires-Dist: tqdm>=4.66.5
Requires-Dist: tomli>=2.0.1
Requires-Dist: cplex>=22.1.2 ; extra == 'cplex'
Requires-Dist: docplex>=2.28.240 ; extra == 'docplex'
Requires-Python: >=3.10
Project-URL: Documentation, https://pyjobshop.org
Project-URL: Homepage, https://pyjobshop.org
Project-URL: Issues, https://github.com/PyJobShop/PyJobShop/issues
Project-URL: Repository, https://github.com/PyJobShop/PyJobShop
Provides-Extra: cplex
Provides-Extra: docplex
